APB_UART_IP/rtl/uart_rx.v
module uart_rx (
    input  wire       clk,
    input  wire       rst_n,
    input  wire       rx,
    input  wire [15:0] baud_div,
    output reg [7:0]  rx_data,
    output reg        rx_valid
);

    reg [3:0] bit_cnt;
    reg [15:0] baud_cnt;
    reg [7:0] data_reg;
    reg receiving;

    always @(posedge clk or negedge rst_n) begin
        if (!rst_n) begin
            rx_valid <= 0;
            receiving <= 0;
            bit_cnt <= 0;
            baud_cnt <= 0;
        end else begin
            rx_valid <= 0;
            if (!receiving && rx == 0) begin
                receiving <= 1;
                baud_cnt <= baud_div >> 1;
                bit_cnt <= 0;
            end else if (receiving) begin
                if (baud_cnt == baud_div - 1) begin
                    baud_cnt <= 0;
                    data_reg[bit_cnt] <= rx;
                    bit_cnt <= bit_cnt + 1;
                    if (bit_cnt == 7) begin
                        receiving <= 0;
                        rx_data <= data_reg;
                        rx_valid <= 1;
                    end
                end else begin
                    baud_cnt <= baud_cnt + 1;
                end
            end
        end
    end
endmodule

APB_UART_IP/rtl/uart_tx.v
module uart_tx (
    input  wire       clk,
    input  wire       rst_n,
    input  wire       tx_start,
    input  wire [7:0] tx_data,
    input  wire [15:0] baud_div,
    output reg        tx,
    output reg        tx_busy
);

    reg [3:0] bit_cnt;
    reg [15:0] baud_cnt;
    reg [9:0] shift_reg;

    always @(posedge clk or negedge rst_n) begin
        if (!rst_n) begin
            tx <= 1'b1;
            tx_busy <= 0;
            bit_cnt <= 0;
            baud_cnt <= 0;
            shift_reg <= 10'h3FF;
        end else begin
            if (tx_start && !tx_busy) begin
                shift_reg <= {1'b1, tx_data, 1'b0}; // stop, data, start
                tx_busy <= 1;
                bit_cnt <= 0;
                baud_cnt <= 0;
            end else if (tx_busy) begin
                if (baud_cnt == baud_div - 1) begin
                    baud_cnt <= 0;
                    tx <= shift_reg[0];
                    shift_reg <= {1'b1, shift_reg[9:1]};
                    bit_cnt <= bit_cnt + 1;
                    if (bit_cnt == 9) begin
                        tx_busy <= 0;
                        tx <= 1'b1;
                    end
                end else begin
                    baud_cnt <= baud_cnt + 1;
                end
            end
        end
    end
endmodule

APB_UART_IP/rtl/uart_top.v
module uart_top (
    input  wire       clk,
    input  wire       rst_n,
    input  wire       tx_start,
    input  wire [7:0] tx_data,
    input  wire [15:0] baud_div,
    output wire       tx,
    output wire       tx_busy,
    input  wire       rx,
    output wire [7:0] rx_data,
    output wire       rx_valid
);

    uart_tx u_tx (
        .clk(clk),
        .rst_n(rst_n),
        .tx_start(tx_start),
        .tx_data(tx_data),
        .baud_div(baud_div),
        .tx(tx),
        .tx_busy(tx_busy)
    );

    uart_rx u_rx (
        .clk(clk),
        .rst_n(rst_n),
        .rx(rx),
        .baud_div(baud_div),
        .rx_data(rx_data),
        .rx_valid(rx_valid)
    );
endmodule

APB_UART_IP/rtl/apb_uart.v
module apb_uart (
    input  wire        PCLK,
    input  wire        PRESETn,
    input  wire        PSEL,
    input  wire        PENABLE,
    input  wire        PWRITE,
    input  wire [7:0]  PADDR,
    input  wire [31:0] PWDATA,
    output reg  [31:0] PRDATA,
    output wire        PREADY,
    output wire        uart_tx,
    input  wire        uart_rx
);

    assign PREADY = 1'b1;

    reg        ctrl_en;
    reg [15:0] baud_div;
    reg [7:0]  rx_reg;
    reg        rx_valid_reg;
    reg        tx_start;

    wire tx_busy;
    wire [7:0] rx_data;
    wire rx_valid;

    uart_top uart (
        .clk(PCLK),
        .rst_n(PRESETn),
        .tx_start(tx_start),
        .tx_data(PWDATA[7:0]),
        .baud_div(baud_div),
        .tx(uart_tx),
        .tx_busy(tx_busy),
        .rx(uart_rx),
        .rx_data(rx_data),
        .rx_valid(rx_valid)
    );

    always @(posedge PCLK or negedge PRESETn) begin
        if (!PRESETn) begin
            ctrl_en <= 0;
            baud_div <= 16'd16;
            tx_start <= 0;
            rx_valid_reg <= 0;
        end else begin
            tx_start <= 0;
            if (PSEL && PENABLE && PWRITE) begin
                case (PADDR)
                    8'h00: ctrl_en <= PWDATA[0];
                    8'h04: baud_div <= PWDATA[15:0];
                    8'h08: if (ctrl_en && !tx_busy) tx_start <= 1;
                endcase
            end
            if (rx_valid) begin
                rx_reg <= rx_data;
                rx_valid_reg <= 1;
            end
            if (PSEL && PENABLE && !PWRITE && PADDR == 8'h0C)
                rx_valid_reg <= 0;
        end
    end

    always @(*) begin
        PRDATA = 32'h0;
        if (PSEL && !PWRITE) begin
            case (PADDR)
                8'h0C: PRDATA = {24'h0, rx_reg};
                8'h10: PRDATA = {30'h0, rx_valid_reg, tx_busy};
            endcase
        end
    end
endmodule

APB_UART_IP/tb/tb_apb_uart.sv
`timescale 1ns/1ps

module tb_apb_uart;

    reg PCLK = 0;
    always #5 PCLK = ~PCLK;

    reg PRESETn;
    reg PSEL, PENABLE, PWRITE;
    reg [7:0] PADDR;
    reg [31:0] PWDATA;
    wire [31:0] PRDATA;
    wire uart_tx;
    reg uart_rx = 1;

    apb_uart dut (
        .PCLK(PCLK),
        .PRESETn(PRESETn),
        .PSEL(PSEL),
        .PENABLE(PENABLE),
        .PWRITE(PWRITE),
        .PADDR(PADDR),
        .PWDATA(PWDATA),
        .PRDATA(PRDATA),
        .PREADY(),
        .uart_tx(uart_tx),
        .uart_rx(uart_rx)
    );

    task apb_write(input [7:0] addr, input [31:0] data);
        begin
            PSEL=1; PWRITE=1; PENABLE=0;
            PADDR=addr; PWDATA=data;
            #10 PENABLE=1;
            #10 PSEL=0; PENABLE=0;
        end
    endtask

    initial begin
        $dumpfile("dump.vcd");
        $dumpvars(0, tb_apb_uart);

        PRESETn=0;
        #20 PRESETn=1;

        apb_write(8'h00, 1);
        apb_write(8'h04, 16);
        apb_write(8'h08, 8'h55);

        #2000;
        $finish;
    end
endmodule

APB_UART_IP/sim/dump.vcd
$date
	Sun Jan 25 21:53:43 2026
$end
$version
	Icarus Verilog
$end
$timescale
	1ps
$end
$scope module tb_apb_uart $end
$var wire 1 ! uart_tx $end
$var wire 32 " PRDATA [31:0] $end
$var reg 8 # PADDR [7:0] $end
$var reg 1 $ PCLK $end
$var reg 1 % PENABLE $end
$var reg 1 & PRESETn $end
$var reg 1 ' PSEL $end
$var reg 32 ( PWDATA [31:0] $end
$var reg 1 ) PWRITE $end
$var reg 1 * uart_rx $end
$scope module dut $end
$var wire 8 + PADDR [7:0] $end
$var wire 1 $ PCLK $end
$var wire 1 % PENABLE $end
$var wire 1 , PREADY $end
$var wire 1 & PRESETn $end
$var wire 1 ' PSEL $end
$var wire 32 - PWDATA [31:0] $end
$var wire 1 ) PWRITE $end
$var wire 1 * uart_rx $end
$var wire 1 ! uart_tx $end
$var wire 1 . tx_busy $end
$var wire 1 / rx_valid $end
$var wire 8 0 rx_data [7:0] $end
$var reg 32 1 PRDATA [31:0] $end
$var reg 16 2 baud_div [15:0] $end
$var reg 1 3 ctrl_en $end
$var reg 8 4 rx_reg [7:0] $end
$var reg 1 5 rx_valid_reg $end
$var reg 1 6 tx_start $end
$scope module uart $end
$var wire 16 7 baud_div [15:0] $end
$var wire 1 $ clk $end
$var wire 1 & rst_n $end
$var wire 1 * rx $end
$var wire 8 8 tx_data [7:0] $end
$var wire 1 6 tx_start $end
$var wire 1 . tx_busy $end
$var wire 1 ! tx $end
$var wire 1 / rx_valid $end
$var wire 8 9 rx_data [7:0] $end
$scope module u_rx $end
$var wire 16 : baud_div [15:0] $end
$var wire 1 $ clk $end
$var wire 1 & rst_n $end
$var wire 1 * rx $end
$var reg 16 ; baud_cnt [15:0] $end
$var reg 4 < bit_cnt [3:0] $end
$var reg 8 = data_reg [7:0] $end
$var reg 1 > receiving $end
$var reg 8 ? rx_data [7:0] $end
$var reg 1 / rx_valid $end
$upscope $end
$scope module u_tx $end
$var wire 16 @ baud_div [15:0] $end
$var wire 1 $ clk $end
$var wire 1 & rst_n $end
$var wire 8 A tx_data [7:0] $end
$var wire 1 6 tx_start $end
$var reg 16 B baud_cnt [15:0] $end
$var reg 4 C bit_cnt [3:0] $end
$var reg 10 D shift_reg [9:0] $end
$var reg 1 ! tx $end
$var reg 1 . tx_busy $end
$upscope $end
$upscope $end
$upscope $end
$scope task apb_write $end
$var reg 8 E addr [7:0] $end
$var reg 32 F data [31:0] $end
$upscope $end
$upscope $end
$enddefinitions $end
$comment Show the parameter values. $end
$dumpall
$end
#0
$dumpvars
bx F
bx E
b1111111111 D
b0 C
b0 B
bx A
b10000 @
bx ?
0>
bx =
b0 <
b0 ;
b10000 :
bx 9
bx 8
b10000 7
06
05
bx 4
03
b10000 2
b0 1
bx 0
0/
0.
bx -
1,
bx +
1*
x)
bx (
x'
0&
x%
0$
bx #
b0 "
1!
$end
#5000
1$
#10000
0$
#15000
1$
#20000
b1 8
b1 A
0$
b1 (
b1 -
b0 #
b0 +
0%
1)
1'
b1 F
b0 E
1&
#25000
1$
#30000
0$
1%
#35000
13
1$
#40000
b10000 8
b10000 A
0$
b10000 (
b10000 -
b100 #
b100 +
b10000 F
b100 E
0%
1'
#45000
1$
#50000
0$
1%
#55000
1$
#60000
b1010101 8
b1010101 A
0$
b1010101 (
b1010101 -
b1000 #
b1000 +
b1010101 F
b1000 E
0%
1'
#65000
1$
#70000
0$
1%
#75000
16
1$
#80000
0$
0%
0'
#85000
06
1.
b1010101010 D
1$
#90000
0$
#95000
b1 B
1$
#100000
0$
#105000
b10 B
1$
#110000
0$
#115000
b11 B
1$
#120000
0$
#125000
b100 B
1$
#130000
0$
#135000
b101 B
1$
#140000
0$
#145000
b110 B
1$
#150000
0$
#155000
b111 B
1$
#160000
0$
#165000
b1000 B
1$
#170000
0$
#175000
b1001 B
1$
#180000
0$
#185000
b1010 B
1$
#190000
0$
#195000
b1011 B
1$
#200000
0$
#205000
b1100 B
1$
#210000
0$
#215000
b1101 B
1$
#220000
0$
#225000
b1110 B
1$
#230000
0$
#235000
b1111 B
1$
#240000
0$
#245000
b1 C
b1101010101 D
0!
b0 B
1$
#250000
0$
#255000
b1 B
1$
#260000
0$
#265000
b10 B
1$
#270000
0$
#275000
b11 B
1$
#280000
0$
#285000
b100 B
1$
#290000
0$
#295000
b101 B
1$
#300000
0$
#305000
b110 B
1$
#310000
0$
#315000
b111 B
1$
#320000
0$
#325000
b1000 B
1$
#330000
0$
#335000
b1001 B
1$
#340000
0$
#345000
b1010 B
1$
#350000
0$
#355000
b1011 B
1$
#360000
0$
#365000
b1100 B
1$
#370000
0$
#375000
b1101 B
1$
#380000
0$
#385000
b1110 B
1$
#390000
0$
#395000
b1111 B
1$
#400000
0$
#405000
b10 C
b1110101010 D
1!
b0 B
1$
#410000
0$
#415000
b1 B
1$
#420000
0$
#425000
b10 B
1$
#430000
0$
#435000
b11 B
1$
#440000
0$
#445000
b100 B
1$
#450000
0$
#455000
b101 B
1$
#460000
0$
#465000
b110 B
1$
#470000
0$
#475000
b111 B
1$
#480000
0$
#485000
b1000 B
1$
#490000
0$
#495000
b1001 B
1$
#500000
0$
#505000
b1010 B
1$
#510000
0$
#515000
b1011 B
1$
#520000
0$
#525000
b1100 B
1$
#530000
0$
#535000
b1101 B
1$
#540000
0$
#545000
b1110 B
1$
#550000
0$
#555000
b1111 B
1$
#560000
0$
#565000
b11 C
b1111010101 D
0!
b0 B
1$
#570000
0$
#575000
b1 B
1$
#580000
0$
#585000
b10 B
1$
#590000
0$
#595000
b11 B
1$
#600000
0$
#605000
b100 B
1$
#610000
0$
#615000
b101 B
1$
#620000
0$
#625000
b110 B
1$
#630000
0$
#635000
b111 B
1$
#640000
0$
#645000
b1000 B
1$
#650000
0$
#655000
b1001 B
1$
#660000
0$
#665000
b1010 B
1$
#670000
0$
#675000
b1011 B
1$
#680000
0$
#685000
b1100 B
1$
#690000
0$
#695000
b1101 B
1$
#700000
0$
#705000
b1110 B
1$
#710000
0$
#715000
b1111 B
1$
#720000
0$
#725000
b100 C
b1111101010 D
1!
b0 B
1$
#730000
0$
#735000
b1 B
1$
#740000
0$
#745000
b10 B
1$
#750000
0$
#755000
b11 B
1$
#760000
0$
#765000
b100 B
1$
#770000
0$
#775000
b101 B
1$
#780000
0$
#785000
b110 B
1$
#790000
0$
#795000
b111 B
1$
#800000
0$
#805000
b1000 B
1$
#810000
0$
#815000
b1001 B
1$
#820000
0$
#825000
b1010 B
1$
#830000
0$
#835000
b1011 B
1$
#840000
0$
#845000
b1100 B
1$
#850000
0$
#855000
b1101 B
1$
#860000
0$
#865000
b1110 B
1$
#870000
0$
#875000
b1111 B
1$
#880000
0$
#885000
b101 C
b1111110101 D
0!
b0 B
1$
#890000
0$
#895000
b1 B
1$
#900000
0$
#905000
b10 B
1$
#910000
0$
#915000
b11 B
1$
#920000
0$
#925000
b100 B
1$
#930000
0$
#935000
b101 B
1$
#940000
0$
#945000
b110 B
1$
#950000
0$
#955000
b111 B
1$
#960000
0$
#965000
b1000 B
1$
#970000
0$
#975000
b1001 B
1$
#980000
0$
#985000
b1010 B
1$
#990000
0$
#995000
b1011 B
1$
#1000000
0$
#1005000
b1100 B
1$
#1010000
0$
#1015000
b1101 B
1$
#1020000
0$
#1025000
b1110 B
1$
#1030000
0$
#1035000
b1111 B
1$
#1040000
0$
#1045000
b110 C
b1111111010 D
1!
b0 B
1$
#1050000
0$
#1055000
b1 B
1$
#1060000
0$
#1065000
b10 B
1$
#1070000
0$
#1075000
b11 B
1$
#1080000
0$
#1085000
b100 B
1$
#1090000
0$
#1095000
b101 B
1$
#1100000
0$
#1105000
b110 B
1$
#1110000
0$
#1115000
b111 B
1$
#1120000
0$
#1125000
b1000 B
1$
#1130000
0$
#1135000
b1001 B
1$
#1140000
0$
#1145000
b1010 B
1$
#1150000
0$
#1155000
b1011 B
1$
#1160000
0$
#1165000
b1100 B
1$
#1170000
0$
#1175000
b1101 B
1$
#1180000
0$
#1185000
b1110 B
1$
#1190000
0$
#1195000
b1111 B
1$
#1200000
0$
#1205000
b111 C
b1111111101 D
0!
b0 B
1$
#1210000
0$
#1215000
b1 B
1$
#1220000
0$
#1225000
b10 B
1$
#1230000
0$
#1235000
b11 B
1$
#1240000
0$
#1245000
b100 B
1$
#1250000
0$
#1255000
b101 B
1$
#1260000
0$
#1265000
b110 B
1$
#1270000
0$
#1275000
b111 B
1$
#1280000
0$
#1285000
b1000 B
1$
#1290000
0$
#1295000
b1001 B
1$
#1300000
0$
#1305000
b1010 B
1$
#1310000
0$
#1315000
b1011 B
1$
#1320000
0$
#1325000
b1100 B
1$
#1330000
0$
#1335000
b1101 B
1$
#1340000
0$
#1345000
b1110 B
1$
#1350000
0$
#1355000
b1111 B
1$
#1360000
0$
#1365000
b1000 C
b1111111110 D
1!
b0 B
1$
#1370000
0$
#1375000
b1 B
1$
#1380000
0$
#1385000
b10 B
1$
#1390000
0$
#1395000
b11 B
1$
#1400000
0$
#1405000
b100 B
1$
#1410000
0$
#1415000
b101 B
1$
#1420000
0$
#1425000
b110 B
1$
#1430000
0$
#1435000
b111 B
1$
#1440000
0$
#1445000
b1000 B
1$
#1450000
0$
#1455000
b1001 B
1$
#1460000
0$
#1465000
b1010 B
1$
#1470000
0$
#1475000
b1011 B
1$
#1480000
0$
#1485000
b1100 B
1$
#1490000
0$
#1495000
b1101 B
1$
#1500000
0$
#1505000
b1110 B
1$
#1510000
0$
#1515000
b1111 B
1$
#1520000
0$
#1525000
b1001 C
b1111111111 D
0!
b0 B
1$
#1530000
0$
#1535000
b1 B
1$
#1540000
0$
#1545000
b10 B
1$
#1550000
0$
#1555000
b11 B
1$
#1560000
0$
#1565000
b100 B
1$
#1570000
0$
#1575000
b101 B
1$
#1580000
0$
#1585000
b110 B
1$
#1590000
0$
#1595000
b111 B
1$
#1600000
0$
#1605000
b1000 B
1$
#1610000
0$
#1615000
b1001 B
1$
#1620000
0$
#1625000
b1010 B
1$
#1630000
0$
#1635000
b1011 B
1$
#1640000
0$
#1645000
b1100 B
1$
#1650000
0$
#1655000
b1101 B
1$
#1660000
0$
#1665000
b1110 B
1$
#1670000
0$
#1675000
b1111 B
1$
#1680000
0$
#1685000
0.
b1010 C
1!
b0 B
1$
